{
  "id": 2,
  "naziv": "AKTON d.o.o. za inženjering i konsalting Sarajevo",
  "komercijalni_naziv": "AKTON",
  "status": "aktivan",
  "opis": "Dio međunarodne Akton grupe osnovane 1991. godine, koja posluje u više zemalja jugoistočne Evrope. Akton je B2B provajder koji nudi veleprodajne i korporativne usluge, uključujući prenos podataka, glasovne usluge i kolokaciju u data centrima.",
  "napomena": "Ključna uloga firme je \"carrier's carrier\" - operater za druge operatere i velike poslovne sisteme. Posjeduju nacionalnu licencu za pružanje veleprodajnih usluga u BiH.",
  "kontakt": {
    "adresa": "Fra Anđela Zvizdovića 1 / A4, 71000 Sarajevo",
    "telefon": "+387 33 296 622",
    "email": "info@akton.ba",
    "web": "https://akton.net/ba/",
    "customer_service": {
      "b2b": "+387 33 296 622"
    },
    "drustvene_mreze": {}
  },
  "tehnicki_kontakti": [],
  "detaljne_usluge": {
    "mobilne": [],
    "fiksne": [
      "fixed_voip"
    ],
    "internet": [
      "internet_business",
      "data_transfer"
    ],
    "tv": [],
    "cloud_poslovne": [
      "colocation",
      "sms_gateway"
    ],
    "dodatne": []
  },
  "detaljne_tehnologije": {
    "mobilne": [],
    "fiksne": [
      "tech_voip_fixed",
      "tech_sip"
    ],
    "mrezne": [
      "tech_mpls",
      "tech_data_center",
      "tech_carrier_grade"
    ]
  },
  "zakonske_obaveze": {
    "zakonito_presretanje": true,
    "pristup_obracunskim_podacima": true,
    "implementacija": "B2B carrier standard",
    "kontakt_osoba": "AKTON tehnicka podrska",
    "email_kontakt": "info@akton.ba",
    "telefon_kontakt": "+387 33 296 622",
    "posjeduje_misljenje_zuo": "Da",
    "napomene": "B2B operater sa nacionalnom licencom za veleprodajne usluge."
  },
  "datum_azuriranja": "2025-09-08",
  "kontakt_osoba": "AKTON tehnicka podrska",
  "kategorija": "alternativni",
  "tipovi": [
    "isp",
    "enterprise"
  ]
}